oneworldsync/__init__.py
oneworldsync/cli.py
oneworldsync/content1_auth.py
oneworldsync/content1_client.py
oneworldsync/criteria.py
oneworldsync/exceptions.py
oneworldsync/models.py
oneworldsync/utils.py
oneworldsync-0.3.3.dist-info/licenses/LICENSE
oneworldsync-0.3.3.dist-info/METADATA
oneworldsync-0.3.3.dist-info/WHEEL
oneworldsync-0.3.3.dist-info/entry_points.txt
oneworldsync-0.3.3.dist-info/top_level.txt
oneworldsync-0.3.3.dist-info/RECORD
