Metadata-Version: 2.4
Name: oneworldsync
Version: 0.3.3
Summary: A Python client for the 1WorldSync Content1 REST API
Home-page: https://github.com/mcgarrah/oneworldsync_python
Author: Michael McGarrah
Author-email: Michael McGarrah <mcgarrah@gmail.com>
License: MIT
Project-URL: Homepage, https://github.com/mcgarrah/oneworldsync_python
Project-URL: Bug Tracker, https://github.com/mcgarrah/oneworldsync_python/issues
Project-URL: Repository, https://github.com/mcgarrah/oneworldsync_python
Project-URL: Documentation, https://oneworldsync-python.readthedocs.io/en/latest/
Classifier: Development Status :: 3 - Alpha
Classifier: Intended Audience :: Developers
Classifier: License :: OSI Approved :: MIT License
Classifier: Programming Language :: Python :: 3
Classifier: Programming Language :: Python :: 3.12
Classifier: Programming Language :: Python :: 3.13
Requires-Python: >=3.12
License-File: LICENSE
Requires-Dist: requests>=2.25.0
Requires-Dist: python-dotenv>=0.15.0
Requires-Dist: click>=8.0.0
Provides-Extra: dev
Requires-Dist: pytest>=6.0; extra == "dev"
Requires-Dist: pytest-cov>=2.10; extra == "dev"
Requires-Dist: black>=22.3; extra == "dev"
Requires-Dist: flake8>=3.9; extra == "dev"
Requires-Dist: mypy>=0.910; extra == "dev"
Requires-Dist: isort>=5.0; extra == "dev"
Requires-Dist: bandit>=1.7; extra == "dev"
Requires-Dist: pre-commit>=2.13; extra == "dev"
Provides-Extra: docs
Requires-Dist: sphinx>=4.0; extra == "docs"
Requires-Dist: sphinx-rtd-theme>=1.0; extra == "docs"
Dynamic: author
Dynamic: home-page
Dynamic: license-file
Dynamic: requires-python
